[{"type":"function","inputs":[{"name":"_valsetArgs","internalType":"struct ValsetArgs","type":"tuple","components":[{"name":"validators","internalType":"address[]","type":"address[]"},{"name":"powers","internalType":"uint256[]","type":"uint256[]"},{"name":"valsetNonce","internalType":"uint256","type":"uint256"},{"name":"rewardAmount","internalType":"uint256","type":"uint256"},{"name":"rewardToken","internalType":"address","type":"address"}]},{"name":"_gravityId","internalType":"bytes32","type":"bytes32"}],"name":"testMakeCheckpoint","outputs":[],"stateMutability":"pure"}]