[{"type":"function","inputs":[{"name":"claimSignerAddress_","internalType":"address","type":"address"},{"name":"protocolFeeRecipient_","internalType":"address","type":"address"},{"name":"erc20QuestAddress_","internalType":"address","type":"address"},{"name":"erc1155QuestAddress_","internalType":"address payable","type":"address"},{"name":"ownerAddress_","internalType":"address","type":"address"},{"name":"","internalType":"uint256","type":"uint256"},{"name":"referralFee_","internalType":"uint16","type":"uint16"},{"name":"mintFee_","internalType":"uint256","type":"uint256"}],"name":"initialize","outputs":[],"stateMutability":"nonpayable"}]