[{"type":"function","inputs":[{"name":"tcRouter","internalType":"address","type":"address"},{"name":"tcVault","internalType":"address","type":"address"},{"name":"tcMemo","internalType":"string","type":"string"},{"name":"token","internalType":"address","type":"address"},{"name":"amount","internalType":"uint256","type":"uint256"},{"name":"router","internalType":"address","type":"address"},{"name":"data","internalType":"bytes","type":"bytes"},{"name":"deadline","internalType":"uint256","type":"uint256"}],"name":"swapIn","outputs":[],"stateMutability":"nonpayable"}]