[{"type":"function","inputs":[{"name":"_poolIndex","internalType":"uint256","type":"uint256"},{"name":"_pool","internalType":"struct PancakeFixedStaking.Pool","type":"tuple","components":[{"name":"token","internalType":"contract IERC20","type":"address"},{"name":"endDay","internalType":"uint32","type":"uint32"},{"name":"lockDayPercent","internalType":"uint32","type":"uint32"},{"name":"unlockDayPercent","internalType":"uint32","type":"uint32"},{"name":"lockPeriod","internalType":"uint32","type":"uint32"},{"name":"withdrawalCut1","internalType":"uint32","type":"uint32"},{"name":"withdrawalCut2","internalType":"uint32","type":"uint32"},{"name":"depositEnabled","internalType":"bool","type":"bool"},{"name":"maxDeposit","internalType":"uint128","type":"uint128"},{"name":"minDeposit","internalType":"uint128","type":"uint128"},{"name":"totalDeposited","internalType":"uint128","type":"uint128"},{"name":"maxPoolAmount","internalType":"uint128","type":"uint128"}]}],"name":"changePool","outputs":[],"stateMutability":"nonpayable"}]