[{"type":"function","inputs":[{"name":"_seed","internalType":"struct Randomizer.Seed","type":"tuple","components":[{"name":"seed","internalType":"uint256","type":"uint256"},{"name":"value","internalType":"uint256","type":"uint256"}]}],"name":"generateProps","outputs":[{"name":"seed","internalType":"struct Randomizer.Seed","type":"tuple","components":[{"name":"seed","internalType":"uint256","type":"uint256"},{"name":"value","internalType":"uint256","type":"uint256"}]},{"name":"props","internalType":"struct SplatterProvider.Props","type":"tuple","components":[{"name":"count","internalType":"uint256","type":"uint256"},{"name":"length","internalType":"uint256","type":"uint256"},{"name":"dot","internalType":"uint256","type":"uint256"}]}],"stateMutability":"pure"}]