[{"type":"function","inputs":[{"name":"old","internalType":"struct IRevest.FNFTConfig","type":"tuple","components":[{"name":"asset","internalType":"address","type":"address"},{"name":"pipeToContract","internalType":"address","type":"address"},{"name":"depositAmount","internalType":"uint256","type":"uint256"},{"name":"depositMul","internalType":"uint256","type":"uint256"},{"name":"split","internalType":"uint256","type":"uint256"},{"name":"depositStopTime","internalType":"uint256","type":"uint256"},{"name":"maturityExtension","internalType":"bool","type":"bool"},{"name":"isMulti","internalType":"bool","type":"bool"},{"name":"nontransferrable","internalType":"bool","type":"bool"}]}],"name":"cloneFNFTConfig","outputs":[{"name":"","internalType":"struct IRevest.FNFTConfig","type":"tuple","components":[{"name":"asset","internalType":"address","type":"address"},{"name":"pipeToContract","internalType":"address","type":"address"},{"name":"depositAmount","internalType":"uint256","type":"uint256"},{"name":"depositMul","internalType":"uint256","type":"uint256"},{"name":"split","internalType":"uint256","type":"uint256"},{"name":"depositStopTime","internalType":"uint256","type":"uint256"},{"name":"maturityExtension","internalType":"bool","type":"bool"},{"name":"isMulti","internalType":"bool","type":"bool"},{"name":"nontransferrable","internalType":"bool","type":"bool"}]}],"stateMutability":"pure"}]