[{"type":"function","inputs":[{"name":"_index","internalType":"uint256","type":"uint256"},{"name":"_user","internalType":"address","type":"address"}],"name":"claimInfoFor","outputs":[{"name":"openTime","internalType":"uint256","type":"uint256"},{"name":"closeTime","internalType":"uint256","type":"uint256"},{"name":"unlocked","internalType":"bool","type":"bool"},{"name":"claimedWTF","internalType":"bool","type":"bool"},{"name":"claimedNFT","internalType":"bool","type":"bool"},{"name":"wethReserve","internalType":"uint256","type":"uint256"},{"name":"wtfReserve","internalType":"uint256","type":"uint256"}],"stateMutability":"view"}]