[{"type":"function","inputs":[{"name":"_lifiData","internalType":"struct ILiFi.LiFiData","type":"tuple","components":[{"name":"transactionId","internalType":"bytes32","type":"bytes32"},{"name":"integrator","internalType":"string","type":"string"},{"name":"referrer","internalType":"address","type":"address"},{"name":"sendingAssetId","internalType":"address","type":"address"},{"name":"receivingAssetId","internalType":"address","type":"address"},{"name":"receiver","internalType":"address","type":"address"},{"name":"destinationChainId","internalType":"uint256","type":"uint256"},{"name":"amount","internalType":"uint256","type":"uint256"}]},{"name":"_swapData","internalType":"struct LibSwap.SwapData[]","type":"tuple[]","components":[{"name":"callTo","internalType":"address","type":"address"},{"name":"approveTo","internalType":"address","type":"address"},{"name":"sendingAssetId","internalType":"address","type":"address"},{"name":"receivingAssetId","internalType":"address","type":"address"},{"name":"fromAmount","internalType":"uint256","type":"uint256"},{"name":"callData","internalType":"bytes","type":"bytes"}]},{"name":"_nxtpData","internalType":"struct ITransactionManager.PrepareArgs","type":"tuple","components":[{"name":"invariantData","internalType":"struct ITransactionManager.InvariantTransactionData","type":"tuple","components":[{"name":"receivingChainTxManagerAddress","internalType":"address","type":"address"},{"name":"user","internalType":"address","type":"address"},{"name":"router","internalType":"address","type":"address"},{"name":"initiator","internalType":"address","type":"address"},{"name":"sendingAssetId","internalType":"address","type":"address"},{"name":"receivingAssetId","internalType":"address","type":"address"},{"name":"sendingChainFallback","internalType":"address","type":"address"},{"name":"receivingAddress","internalType":"address","type":"address"},{"name":"callTo","internalType":"address","type":"address"},{"name":"sendingChainId","internalType":"uint256","type":"uint256"},{"name":"receivingChainId","internalType":"uint256","type":"uint256"},{"name":"callDataHash","internalType":"bytes32","type":"bytes32"},{"name":"transactionId","internalType":"bytes32","type":"bytes32"}]},{"name":"amount","internalType":"uint256","type":"uint256"},{"name":"expiry","internalType":"uint256","type":"uint256"},{"name":"encryptedCallData","internalType":"bytes","type":"bytes"},{"name":"encodedBid","internalType":"bytes","type":"bytes"},{"name":"bidSignature","internalType":"bytes","type":"bytes"},{"name":"encodedMeta","internalType":"bytes","type":"bytes"}]}],"name":"swapAndStartBridgeTokensViaNXTP","outputs":[],"stateMutability":"payable"}]