[{"type":"function","inputs":[{"name":"","internalType":"address","type":"address"}],"name":"issuers","outputs":[{"name":"collateral","internalType":"uint256","type":"uint256"},{"name":"commissionRate","internalType":"uint256","type":"uint256"},{"name":"adminCommissionRate","internalType":"uint256","type":"uint256"},{"name":"mtmPayables","internalType":"uint256","type":"uint256"},{"name":"actualPayables","internalType":"uint256","type":"uint256"},{"name":"isHardThresholdReached","internalType":"bool","type":"bool"},{"name":"isSoftThresholdReached","internalType":"bool","type":"bool"},{"name":"isActive","internalType":"bool","type":"bool"},{"name":"priceFeedDomain","internalType":"enum Issuer.PriceFeedDomain","type":"uint8"}],"stateMutability":"view"}]