[{"type":"function","inputs":[{"name":"fromToken","internalType":"contract IERC20","type":"address"},{"name":"toToken","internalType":"contract IERC20","type":"address"},{"name":"maxAmountIn","internalType":"uint256","type":"uint256"},{"name":"amountOut","internalType":"uint256","type":"uint256"},{"name":"recipient","internalType":"address","type":"address"},{"name":"deadline","internalType":"uint256","type":"uint256"}],"name":"swapTo","outputs":[{"name":"amountIn","internalType":"uint256","type":"uint256"}],"stateMutability":"nonpayable"}]