[{"type":"function","inputs":[{"name":"_request","internalType":"struct XBridge.SwapBridgeRequestV2","type":"tuple","components":[{"name":"fromToken","internalType":"address","type":"address"},{"name":"toToken","internalType":"address","type":"address"},{"name":"to","internalType":"address","type":"address"},{"name":"adaptorId","internalType":"uint256","type":"uint256"},{"name":"toChainId","internalType":"uint256","type":"uint256"},{"name":"fromTokenAmount","internalType":"uint256","type":"uint256"},{"name":"toTokenMinAmount","internalType":"uint256","type":"uint256"},{"name":"toChainToTokenMinAmount","internalType":"uint256","type":"uint256"},{"name":"data","internalType":"bytes","type":"bytes"},{"name":"dexData","internalType":"bytes","type":"bytes"},{"name":"extData","internalType":"bytes","type":"bytes"}]},{"name":"_signature","internalType":"bytes","type":"bytes"}],"name":"swapBridgeToWithPermit","outputs":[],"stateMutability":"nonpayable"}]