[{"type":"function","inputs":[{"name":"_lifiData","internalType":"struct ILiFi.LiFiData","type":"tuple","components":[{"name":"transactionId","internalType":"bytes32","type":"bytes32"},{"name":"integrator","internalType":"string","type":"string"},{"name":"referrer","internalType":"address","type":"address"},{"name":"sendingAssetId","internalType":"address","type":"address"},{"name":"receivingAssetId","internalType":"address","type":"address"},{"name":"receiver","internalType":"address","type":"address"},{"name":"destinationChainId","internalType":"uint256","type":"uint256"},{"name":"amount","internalType":"uint256","type":"uint256"}]},{"name":"_stargateData","internalType":"struct StargateFacet.StargateData","type":"tuple","components":[{"name":"router","internalType":"address","type":"address"},{"name":"dstChainId","internalType":"uint16","type":"uint16"},{"name":"srcPoolId","internalType":"uint256","type":"uint256"},{"name":"dstPoolId","internalType":"uint256","type":"uint256"},{"name":"amountLD","internalType":"uint256","type":"uint256"},{"name":"minAmountLD","internalType":"uint256","type":"uint256"},{"name":"dstGasForCall","internalType":"uint256","type":"uint256"},{"name":"callTo","internalType":"bytes","type":"bytes"},{"name":"callData","internalType":"bytes","type":"bytes"}]}],"name":"startBridgeTokensViaStargate","outputs":[],"stateMutability":"payable"}]