[{"type":"function","inputs":[{"name":"_owner","internalType":"address","type":"address"},{"name":"_editionConfig","internalType":"struct EditionConfig","type":"tuple","components":[{"name":"name","internalType":"string","type":"string"},{"name":"symbol","internalType":"string","type":"string"},{"name":"hasAdjustableCap","internalType":"bool","type":"bool"},{"name":"isSoulbound","internalType":"bool","type":"bool"},{"name":"maxTokens","internalType":"uint256","type":"uint256"},{"name":"tokenPrice","internalType":"uint256","type":"uint256"},{"name":"maxTokenPurchase","internalType":"uint256","type":"uint256"},{"name":"presaleMerkleRoot","internalType":"bytes32","type":"bytes32"},{"name":"presaleStart","internalType":"uint256","type":"uint256"},{"name":"presaleEnd","internalType":"uint256","type":"uint256"},{"name":"saleStart","internalType":"uint256","type":"uint256"},{"name":"saleEnd","internalType":"uint256","type":"uint256"},{"name":"royaltyBPS","internalType":"uint256","type":"uint256"},{"name":"payoutAddress","internalType":"address","type":"address"}]},{"name":"_metadataConfig","internalType":"struct MetadataConfig","type":"tuple","components":[{"name":"contractURI","internalType":"string","type":"string"},{"name":"metadataURI","internalType":"string","type":"string"},{"name":"metadataRendererInit","internalType":"bytes","type":"bytes"},{"name":"parentIP","internalType":"address","type":"address"}]},{"name":"_tokenGateConfig","internalType":"struct TokenGateConfig","type":"tuple","components":[{"name":"tokenAddress","internalType":"address","type":"address"},{"name":"minBalance","internalType":"uint88","type":"uint88"},{"name":"saleType","internalType":"enum SaleType","type":"uint8"}]},{"name":"_metadataRenderer","internalType":"address","type":"address"},{"name":"_splitMain","internalType":"address","type":"address"}],"name":"initialize","outputs":[],"stateMutability":"nonpayable"}]