[{"type":"function","inputs":[{"name":"_fundingRecipient","internalType":"address payable","type":"address"},{"name":"_price","internalType":"uint256","type":"uint256"},{"name":"_quantity","internalType":"uint32","type":"uint32"},{"name":"_royaltyBPS","internalType":"uint32","type":"uint32"},{"name":"_startTime","internalType":"uint32","type":"uint32"},{"name":"_endTime","internalType":"uint32","type":"uint32"},{"name":"_permissionedQuantity","internalType":"uint32","type":"uint32"},{"name":"_signerAddress","internalType":"address","type":"address"}],"name":"createEdition","outputs":[],"stateMutability":"nonpayable"}]