[{"type":"function","inputs":[{"name":"trade","internalType":"struct LSSVMRouter.NFTsForSpecificNFTsTrade","type":"tuple","components":[{"name":"nftToTokenTrades","internalType":"struct LSSVMRouter.PairSwapSpecific[]","type":"tuple[]","components":[{"name":"pair","internalType":"contract LSSVMPair","type":"address"},{"name":"nftIds","internalType":"uint256[]","type":"uint256[]"}]},{"name":"tokenToNFTTrades","internalType":"struct LSSVMRouter.PairSwapSpecific[]","type":"tuple[]","components":[{"name":"pair","internalType":"contract LSSVMPair","type":"address"},{"name":"nftIds","internalType":"uint256[]","type":"uint256[]"}]}]},{"name":"inputAmount","internalType":"uint256","type":"uint256"},{"name":"minOutput","internalType":"uint256","type":"uint256"},{"name":"nftRecipient","internalType":"address","type":"address"},{"name":"deadline","internalType":"uint256","type":"uint256"}],"name":"swapNFTsForSpecificNFTsThroughERC20","outputs":[{"name":"outputAmount","internalType":"uint256","type":"uint256"}],"stateMutability":"nonpayable"}]