[{"type":"function","inputs":[{"name":"_aoTAPTokenID","internalType":"uint256","type":"uint256"},{"name":"_paymentToken","internalType":"contract ERC20","type":"address"},{"name":"_tapAmount","internalType":"uint256","type":"uint256"}],"name":"getOTCDealDetails","outputs":[{"name":"eligibleTapAmount","internalType":"uint256","type":"uint256"},{"name":"paymentTokenAmount","internalType":"uint256","type":"uint256"},{"name":"tapAmount","internalType":"uint256","type":"uint256"}],"stateMutability":"view"}]