[{"type":"function","inputs":[{"name":"asset_","internalType":"contract IERC20","type":"address"},{"name":"_name","internalType":"string","type":"string"},{"name":"_symbol","internalType":"string","type":"string"},{"name":"_useNativeAsset","internalType":"bool","type":"bool"},{"name":"_harvestInterval","internalType":"uint256","type":"uint256"},{"name":"_maxTvl","internalType":"uint256","type":"uint256"},{"name":"authConfig","internalType":"struct AuthConfig","type":"tuple","components":[{"name":"owner","internalType":"address","type":"address"},{"name":"guardian","internalType":"address","type":"address"},{"name":"manager","internalType":"address","type":"address"}]},{"name":"feeConfig","internalType":"struct FeeConfig","type":"tuple","components":[{"name":"treasury","internalType":"address","type":"address"},{"name":"performanceFee","internalType":"uint256","type":"uint256"},{"name":"managementFee","internalType":"uint256","type":"uint256"}]}],"name":"initialize","outputs":[],"stateMutability":"nonpayable"}]