[{"type":"function","inputs":[{"name":"_initialOwner","internalType":"address","type":"address"},{"name":"_collectionName","internalType":"string","type":"string"},{"name":"_collectionSymbol","internalType":"string","type":"string"},{"name":"_baseTokenURI","internalType":"string","type":"string"},{"name":"_metadataRenderer","internalType":"address","type":"address"},{"name":"_transferValidator","internalType":"address","type":"address"},{"name":"_royaltyFeeNumerator","internalType":"uint96","type":"uint96"}],"name":"initialize","outputs":[],"stateMutability":"nonpayable"}]