[{"type":"function","inputs":[{"name":"_setToken","internalType":"contract ISetToken","type":"address"},{"name":"_outputToken","internalType":"contract IERC20","type":"address"},{"name":"_amountSetToken","internalType":"uint256","type":"uint256"},{"name":"_minOutputReceive","internalType":"uint256","type":"uint256"},{"name":"_componentQuotes","internalType":"bytes[]","type":"bytes[]"},{"name":"_issuanceModule","internalType":"address","type":"address"},{"name":"_isDebtIssuance","internalType":"bool","type":"bool"}],"name":"redeemExactSetForToken","outputs":[{"name":"","internalType":"uint256","type":"uint256"}],"stateMutability":"nonpayable"}]