[{"type":"function","inputs":[{"name":"_projectName","internalType":"string","type":"string"},{"name":"_lambHash","internalType":"string","type":"string"},{"name":"_projectLicense","internalType":"string","type":"string"},{"name":"_projectWebsite","internalType":"string","type":"string"},{"name":"_projectDescription","internalType":"string","type":"string"},{"name":"_tags","internalType":"string","type":"string"},{"name":"_viewport","internalType":"string","type":"string"},{"name":"_renderDelay","internalType":"uint256","type":"uint256"}],"name":"addProject","outputs":[],"stateMutability":"nonpayable"}]