[{"type":"function","inputs":[{"name":"seasonId","internalType":"uint256","type":"uint256"},{"name":"userWallet","internalType":"address","type":"address"}],"name":"seasonIdToUserToStakeInfo","outputs":[{"name":"erc20balance","internalType":"uint256","type":"uint256"},{"name":"erc20initial","internalType":"uint256","type":"uint256"},{"name":"accumulatedPoints","internalType":"uint256","type":"uint256"},{"name":"lastUpdatedTime","internalType":"uint64","type":"uint64"},{"name":"multiplier","internalType":"uint16","type":"uint16"}],"stateMutability":"view"}]