[{"type":"function","inputs":[],"name":"PRESALE_FEE_INFO","outputs":[{"name":"UNICRYPT_BASE_FEE","internalType":"uint256","type":"uint256"},{"name":"UNICRYPT_TOKEN_FEE","internalType":"uint256","type":"uint256"},{"name":"REFERRAL_FEE","internalType":"uint256","type":"uint256"},{"name":"BASE_FEE_ADDRESS","internalType":"address payable","type":"address"},{"name":"TOKEN_FEE_ADDRESS","internalType":"address payable","type":"address"},{"name":"REFERRAL_FEE_ADDRESS","internalType":"address payable","type":"address"}],"stateMutability":"view"}]