[{"type":"function","inputs":[{"name":"editionId","internalType":"uint256","type":"uint256"}],"name":"getEdition","outputs":[{"name":"","internalType":"struct EditionStorage.Edition","type":"tuple","components":[{"name":"tokenURI","internalType":"string","type":"string"},{"name":"merkleRoot","internalType":"bytes32","type":"bytes32"},{"name":"price","internalType":"uint256","type":"uint256"},{"name":"quantity","internalType":"uint256","type":"uint256"},{"name":"maxQuantity","internalType":"uint256","type":"uint256"},{"name":"maxPerWallet","internalType":"uint256","type":"uint256"},{"name":"maxPerMint","internalType":"uint256","type":"uint256"},{"name":"nonce","internalType":"uint256","type":"uint256"},{"name":"signer","internalType":"address","type":"address"},{"name":"active","internalType":"bool","type":"bool"}]}],"stateMutability":"view"}]