[{"type":"function","inputs":[{"name":"","internalType":"contract ERC20","type":"address"}],"name":"withdrawAssets","outputs":[{"name":"allowWithdraws","internalType":"bool","type":"bool"},{"name":"withdrawDelay","internalType":"uint32","type":"uint32"},{"name":"outstandingShares","internalType":"uint128","type":"uint128"},{"name":"withdrawFee","internalType":"uint16","type":"uint16"},{"name":"maxLoss","internalType":"uint16","type":"uint16"},{"name":"maxWithdrawPerUser","internalType":"uint256","type":"uint256"}],"stateMutability":"view"}]