[{"type":"function","inputs":[{"name":"_defaultAdmin","internalType":"address","type":"address"},{"name":"_trustedForwarders","internalType":"address[]","type":"address[]"},{"name":"_tokenOwner","internalType":"address","type":"address"},{"name":"_airdropTokenAddress","internalType":"address","type":"address"},{"name":"_tokenIds","internalType":"uint256[]","type":"uint256[]"},{"name":"_availableAmounts","internalType":"uint256[]","type":"uint256[]"},{"name":"_expirationTimestamp","internalType":"uint256","type":"uint256"},{"name":"_maxWalletClaimCount","internalType":"uint256[]","type":"uint256[]"},{"name":"_merkleRoot","internalType":"bytes32[]","type":"bytes32[]"}],"name":"initialize","outputs":[],"stateMutability":"nonpayable"}]