[{"type":"function","inputs":[{"name":"_trade","internalType":"struct ITradingStorage.Trade","type":"tuple","components":[{"name":"trader","internalType":"address","type":"address"},{"name":"pairIndex","internalType":"uint256","type":"uint256"},{"name":"index","internalType":"uint256","type":"uint256"},{"name":"initialPosToken","internalType":"uint256","type":"uint256"},{"name":"positionSizeUSDC","internalType":"uint256","type":"uint256"},{"name":"openPrice","internalType":"uint256","type":"uint256"},{"name":"buy","internalType":"bool","type":"bool"},{"name":"leverage","internalType":"uint256","type":"uint256"},{"name":"tp","internalType":"uint256","type":"uint256"},{"name":"sl","internalType":"uint256","type":"uint256"},{"name":"timestamp","internalType":"uint256","type":"uint256"}]},{"name":"_tradeInfo","internalType":"struct ITradingStorage.TradeInfo","type":"tuple","components":[{"name":"openInterestUSDC","internalType":"uint256","type":"uint256"},{"name":"tpLastUpdated","internalType":"uint256","type":"uint256"},{"name":"slLastUpdated","internalType":"uint256","type":"uint256"},{"name":"beingMarketClosed","internalType":"bool","type":"bool"},{"name":"lossProtection","internalType":"uint256","type":"uint256"}]}],"name":"storeTrade","outputs":[],"stateMutability":"nonpayable"}]