[{"type":"function","inputs":[{"name":"bindTokens","internalType":"struct ProxyStruct.BindToken[]","type":"tuple[]","components":[{"name":"token","internalType":"address","type":"address"},{"name":"balance","internalType":"uint256","type":"uint256"},{"name":"weight","internalType":"uint80","type":"uint80"},{"name":"oracle","internalType":"address","type":"address"}]},{"name":"factory","internalType":"contract IFactory","type":"address"},{"name":"finalize","internalType":"bool","type":"bool"},{"name":"deadline","internalType":"uint256","type":"uint256"}],"name":"createPool","outputs":[{"name":"poolAddress","internalType":"address","type":"address"}],"stateMutability":"payable"}]