[{"type":"function","inputs":[{"name":"user","internalType":"address","type":"address"}],"name":"getUserAccountData","outputs":[{"name":"totalCollateralBase","internalType":"uint256","type":"uint256"},{"name":"totalDebtBase","internalType":"uint256","type":"uint256"},{"name":"availableBorrowsBase","internalType":"uint256","type":"uint256"},{"name":"currentLiquidationThreshold","internalType":"uint256","type":"uint256"},{"name":"ltv","internalType":"uint256","type":"uint256"},{"name":"healthFactor","internalType":"uint256","type":"uint256"}],"stateMutability":"view"}]