[{"type":"function","inputs":[{"name":"tokenAddress","internalType":"address","type":"address"}],"name":"collectionPaymentSettings","outputs":[{"name":"","internalType":"struct CollectionPaymentSettings","type":"tuple","components":[{"name":"paymentSettings","internalType":"enum PaymentSettings","type":"uint8"},{"name":"paymentMethodWhitelistId","internalType":"uint32","type":"uint32"},{"name":"constrainedPricingPaymentMethod","internalType":"address","type":"address"},{"name":"royaltyBackfillNumerator","internalType":"uint16","type":"uint16"},{"name":"royaltyBountyNumerator","internalType":"uint16","type":"uint16"},{"name":"isRoyaltyBountyExclusive","internalType":"bool","type":"bool"},{"name":"blockTradesFromUntrustedChannels","internalType":"bool","type":"bool"},{"name":"blockBannedAccounts","internalType":"bool","type":"bool"}]}],"stateMutability":"view"}]