[{"type":"function","inputs":[{"name":"mToken","internalType":"address","type":"address"}],"name":"channelSettings","outputs":[{"name":"mToken","internalType":"address","type":"address"},{"name":"mTokenDecimals","internalType":"uint8","type":"uint8"},{"name":"withdrawQueue","internalType":"address","type":"address"},{"name":"stakePaused","internalType":"bool","type":"bool"},{"name":"withdrawPaused","internalType":"bool","type":"bool"},{"name":"registered","internalType":"bool","type":"bool"},{"name":"index","internalType":"uint256","type":"uint256"}],"stateMutability":"view"}]