[{"type":"function","inputs":[{"name":"_submissionData","internalType":"struct ILineaRollup.SubmissionDataV2","type":"tuple","components":[{"name":"finalStateRootHash","internalType":"bytes32","type":"bytes32"},{"name":"firstBlockInData","internalType":"uint256","type":"uint256"},{"name":"finalBlockInData","internalType":"uint256","type":"uint256"},{"name":"snarkHash","internalType":"bytes32","type":"bytes32"},{"name":"compressedData","internalType":"bytes","type":"bytes"}]},{"name":"_parentShnarf","internalType":"bytes32","type":"bytes32"},{"name":"_expectedShnarf","internalType":"bytes32","type":"bytes32"}],"name":"submitDataAsCalldata","outputs":[],"stateMutability":"nonpayable"}]