[{"type":"function","inputs":[{"name":"walletPubKeyHash","internalType":"bytes20","type":"bytes20"},{"name":"mainUtxo","internalType":"struct BitcoinTx.UTXO","type":"tuple","components":[{"name":"txHash","internalType":"bytes32","type":"bytes32"},{"name":"txOutputIndex","internalType":"uint32","type":"uint32"},{"name":"txOutputValue","internalType":"uint64","type":"uint64"}]},{"name":"redeemerOutputScript","internalType":"bytes","type":"bytes"},{"name":"amount","internalType":"uint64","type":"uint64"}],"name":"requestRedemption","outputs":[],"stateMutability":"nonpayable"}]