[{"type":"function","inputs":[{"name":"user","internalType":"address","type":"address"}],"name":"userWithdrawals","outputs":[{"name":"","internalType":"struct IDelayedWithdrawalRouter.UserDelayedWithdrawals","type":"tuple","components":[{"name":"delayedWithdrawalsCompleted","internalType":"uint256","type":"uint256"},{"name":"delayedWithdrawals","internalType":"struct IDelayedWithdrawalRouter.DelayedWithdrawal[]","type":"tuple[]","components":[{"name":"amount","internalType":"uint224","type":"uint224"},{"name":"blockCreated","internalType":"uint32","type":"uint32"}]}]}],"stateMutability":"view"}]