[{"type":"function","inputs":[{"name":"assetOut","internalType":"address","type":"address"},{"name":"secondsToMaturity","internalType":"uint24","type":"uint24"},{"name":"minimumSecondsToDeadline","internalType":"uint24","type":"uint24"},{"name":"minDiscount","internalType":"uint16","type":"uint16"},{"name":"maxDiscount","internalType":"uint16","type":"uint16"},{"name":"minimumShares","internalType":"uint96","type":"uint96"}],"name":"updateWithdrawAsset","outputs":[],"stateMutability":"nonpayable"}]