[{"type":"function","inputs":[{"name":"srcTick","internalType":"uint128","type":"uint128"},{"name":"dstTick","internalType":"uint128","type":"uint128"},{"name":"redemptionId","internalType":"uint128","type":"uint128"},{"name":"minShares","internalType":"uint256","type":"uint256"}],"name":"rebalance","outputs":[{"name":"","internalType":"uint256","type":"uint256"},{"name":"","internalType":"uint256","type":"uint256"},{"name":"","internalType":"uint256","type":"uint256"}],"stateMutability":"nonpayable"}]