[{"type":"function","inputs":[{"name":"_metaRevertTransaction","internalType":"struct MetaRouteStructs.MetaRevertTransaction","type":"tuple","components":[{"name":"stableBridgingFee","internalType":"uint256","type":"uint256"},{"name":"internalID","internalType":"bytes32","type":"bytes32"},{"name":"receiveSide","internalType":"address","type":"address"},{"name":"managerChainBridge","internalType":"address","type":"address"},{"name":"sourceChainBridge","internalType":"address","type":"address"},{"name":"managerChainId","internalType":"uint256","type":"uint256"},{"name":"sourceChainId","internalType":"uint256","type":"uint256"},{"name":"router","internalType":"address","type":"address"},{"name":"swapCalldata","internalType":"bytes","type":"bytes"},{"name":"sourceChainSynthesis","internalType":"address","type":"address"},{"name":"burnToken","internalType":"address","type":"address"},{"name":"burnCalldata","internalType":"bytes","type":"bytes"},{"name":"clientID","internalType":"bytes32","type":"bytes32"}]}],"name":"metaRevertRequest","outputs":[],"stateMutability":"nonpayable"}]