[{"type":"function","inputs":[{"name":"_trade","internalType":"struct YakRouter.Trade","type":"tuple","components":[{"name":"amountIn","internalType":"uint256","type":"uint256"},{"name":"amountOut","internalType":"uint256","type":"uint256"},{"name":"path","internalType":"address[]","type":"address[]"},{"name":"adapters","internalType":"address[]","type":"address[]"}]},{"name":"_to","internalType":"address","type":"address"},{"name":"_fee","internalType":"uint256","type":"uint256"}],"name":"swapNoSplitFromAVAX","outputs":[],"stateMutability":"payable"}]