[{"type":"event","anonymous":false,"inputs":[{"name":"account","internalType":"address","type":"address","indexed":false},{"name":"tokenIn","internalType":"address","type":"address","indexed":false},{"name":"tokenOut","internalType":"address","type":"address","indexed":false},{"name":"amountIn","internalType":"uint256","type":"uint256","indexed":false},{"name":"amountOut","internalType":"uint256","type":"uint256","indexed":false},{"name":"amountOutAfterFees","internalType":"uint256","type":"uint256","indexed":false},{"name":"feeBasisPoints","internalType":"uint256","type":"uint256","indexed":false}],"name":"Swap"},{"type":"event","anonymous":false,"inputs":[{"name":"pool","internalType":"address","type":"address","indexed":true},{"name":"tokenIn","internalType":"contract IERC20","type":"address","indexed":true},{"name":"tokenOut","internalType":"contract IERC20","type":"address","indexed":true},{"name":"amountIn","internalType":"uint256","type":"uint256","indexed":false},{"name":"amountOut","internalType":"uint256","type":"uint256","indexed":false},{"name":"swapFeePercentage","internalType":"uint256","type":"uint256","indexed":false},{"name":"swapFeeAmount","internalType":"uint256","type":"uint256","indexed":false}],"name":"Swap"}]