[{"type":"event","anonymous":false,"inputs":[{"name":"mToken","internalType":"address","type":"address","indexed":true},{"name":"acceptTokens","internalType":"struct IManager.AcceptTokenInfo[]","type":"tuple[]","components":[{"name":"addr","internalType":"address","type":"address"},{"name":"chainId","internalType":"uint256","type":"uint256"},{"name":"decimals","internalType":"uint8","type":"uint8"},{"name":"minDepositAmount","internalType":"uint256","type":"uint256"},{"name":"tokenReceiverInfos","internalType":"struct IManager.TokenReceiverInfo[]","type":"tuple[]","components":[{"name":"addr","internalType":"address","type":"address"},{"name":"ratio","internalType":"uint256","type":"uint256"}]}],"indexed":false}],"name":"AddAcceptTokens"}]