[{"type":"event","anonymous":false,"inputs":[{"name":"account","internalType":"address","type":"address","indexed":false},{"name":"slot","internalType":"uint256","type":"uint256","indexed":false},{"name":"unlockTime","internalType":"uint256","type":"uint256","indexed":false},{"name":"lockedAmount","internalType":"uint256","type":"uint256","indexed":false},{"name":"originalVeAmount","internalType":"uint256","type":"uint256","indexed":false},{"name":"newVeAmount","internalType":"uint256","type":"uint256","indexed":false}],"name":"ExtendLock"}]