[{"type":"event","anonymous":false,"inputs":[{"name":"minRedeemRatio","internalType":"uint256","type":"uint256","indexed":false},{"name":"maxRedeemRatio","internalType":"uint256","type":"uint256","indexed":false},{"name":"minRedeemDuration","internalType":"uint256","type":"uint256","indexed":false},{"name":"maxRedeemDuration","internalType":"uint256","type":"uint256","indexed":false},{"name":"redeemDividendsAdjustment","internalType":"uint256","type":"uint256","indexed":false}],"name":"UpdateRedeemSettings"}]