[{"type":"event","anonymous":false,"inputs":[{"name":"_cosmosDenom","internalType":"string","type":"string","indexed":false},{"name":"_tokenContract","internalType":"address","type":"address","indexed":true},{"name":"_name","internalType":"string","type":"string","indexed":false},{"name":"_symbol","internalType":"string","type":"string","indexed":false},{"name":"_decimals","internalType":"uint8","type":"uint8","indexed":false},{"name":"_eventNonce","internalType":"uint256","type":"uint256","indexed":false}],"name":"ERC20DeployedEvent"}]