[{"type":"event","anonymous":false,"inputs":[{"name":"_aggregatorAdaptor","internalType":"address","type":"address","indexed":true},{"name":"_fromToken","internalType":"contract IERC20","type":"address","indexed":true},{"name":"_fromTokenAmount","internalType":"uint256","type":"uint256","indexed":false},{"name":"_toToken","internalType":"contract IERC20","type":"address","indexed":false},{"name":"_toTokenAmountOut","internalType":"uint256","type":"uint256","indexed":false},{"name":"_receiver","internalType":"address","type":"address","indexed":false}],"name":"SwappedForUser"}]