[{"type":"event","anonymous":false,"inputs":[{"name":"hash","type":"bytes32","indexed":true},{"name":"howToCall","type":"uint8","indexed":false},{"name":"calldata","type":"bytes","indexed":false},{"name":"replacementPattern","type":"bytes","indexed":false},{"name":"staticTarget","type":"address","indexed":false},{"name":"staticExtradata","type":"bytes","indexed":false},{"name":"paymentToken","type":"address","indexed":false},{"name":"basePrice","type":"uint256","indexed":false},{"name":"extra","type":"uint256","indexed":false},{"name":"listingTime","type":"uint256","indexed":false},{"name":"expirationTime","type":"uint256","indexed":false},{"name":"salt","type":"uint256","indexed":false},{"name":"orderbookInclusionDesired","type":"bool","indexed":false}],"name":"OrderApprovedPartTwo"}]