[{"type":"event","anonymous":false,"inputs":[{"name":"oldPendingImplementation","internalType":"address","type":"address","indexed":false},{"name":"newPendingImplementation","internalType":"address","type":"address","indexed":false}],"name":"NewPendingImplementation"},{"type":"event","anonymous":false,"inputs":[{"name":"pendingImplementation","internalType":"address","type":"address","indexed":true},{"name":"newImplementation","internalType":"address","type":"address","indexed":true}],"name":"NewPendingImplementation"}]